[
  {
    "phase": "train",
    "batch_idx": 0,
    "batch_size": 4,
    "global_mean": 0.0022281664423644543,
    "global_std": 0.0039055573288351297,
    "var_zero_mean": 1.5252446246449836e-05,
    "per_patch": [
      {
        "patch_idx": 0,
        "mean": 0.0022281857673078775,
        "std": 0.0039059531409293413,
        "min": 0.0,
        "max": 0.01274329237639904
      },
      {
        "patch_idx": 1,
        "mean": 0.0022281778510659933,
        "std": 0.0039059328846633434,
        "min": 0.0,
        "max": 0.012743709608912468
      },
      {
        "patch_idx": 2,
        "mean": 0.002228083088994026,
        "std": 0.0039057722315192223,
        "min": 0.0,
        "max": 0.012743146158754826
      },
      {
        "patch_idx": 3,
        "mean": 0.0022282188292592764,
        "std": 0.0039060006383806467,
        "min": 0.0,
        "max": 0.012743139639496803
      }
    ]
  },
  {
    "phase": "train",
    "batch_idx": 0,
    "batch_size": 4,
    "global_mean": 0.0022280393168330193,
    "global_std": 0.003905334509909153,
    "var_zero_mean": 1.5250705473590642e-05,
    "per_patch": [
      {
        "patch_idx": 0,
        "mean": 0.0022279955446720123,
        "std": 0.0039056253153830767,
        "min": 0.0,
        "max": 0.012743409723043442
      },
      {
        "patch_idx": 1,
        "mean": 0.002227979013696313,
        "std": 0.0039055936504155397,
        "min": 0.0,
        "max": 0.012742405757308006
      },
      {
        "patch_idx": 2,
        "mean": 0.002228152472525835,
        "std": 0.0039058744441717863,
        "min": 0.0,
        "max": 0.012742025777697563
      },
      {
        "patch_idx": 3,
        "mean": 0.002228029537945986,
        "std": 0.0039056746754795313,
        "min": 0.0,
        "max": 0.01274323184043169
      }
    ]
  }
]