[
  {
    "phase": "inference",
    "batch_idx": 0,
    "batch_size": 128,
    "global_mean": 765.819580078125,
    "global_std": 1397.8057861328125,
    "var_zero_mean": 1953579.0,
    "per_patch": [
      {
        "patch_idx": 0,
        "mean": 753.3809204101562,
        "std": 1371.9649658203125,
        "min": 0.0,
        "max": 5044.67822265625
      },
      {
        "patch_idx": 1,
        "mean": 792.812255859375,
        "std": 1448.481689453125,
        "min": 0.0,
        "max": 5084.12841796875
      },
      {
        "patch_idx": 2,
        "mean": 762.9544677734375,
        "std": 1399.9486083984375,
        "min": 0.0,
        "max": 5364.94677734375
      },
      {
        "patch_idx": 3,
        "mean": 759.7017822265625,
        "std": 1370.4072265625,
        "min": 0.0,
        "max": 4654.26025390625
      }
    ]
  }
]